risipy/__init__.py
risipy-0.0.1.dist-info/LICENSE
risipy-0.0.1.dist-info/METADATA
risipy-0.0.1.dist-info/WHEEL
risipy-0.0.1.dist-info/top_level.txt
risipy-0.0.1.dist-info/RECORD
