Metadata-Version: 2.1
Name: risipy
Version: 0.0.1
Summary: A package for getting risistas pics
Home-page: https://github.com/pypa/risipy
Author: Landry JUGE
Author-email: contact@landryjuge.com
License: UNKNOWN
Platform: UNKNOWN
Classifier: Programming Language :: Python :: 3
Classifier: License :: OSI Approved :: MIT License
Classifier: Operating System :: OS Independent
Requires-Python: >=3.6
Requires-Dist: requests
